{
  "created_at": "Wed May 02 07:36:33 +0000 2018",
  "id": "991582200616271872",
  "text": "my favorite thing is when I'm writing a media journal and realize in retrospect that I actually liked the media more than I thought I had",
  "truncated": false,
  "source": "<a href=\"https://about.twitter.com/products/tweetdeck\" rel=\"nofollow\">TweetDeck</a>",
  "user": {
    "name": "Blue Gay Carmen San Diego",
    "screen_name": "nex3"
  },
  "geo": null,
  "coordinates": null,
  "place": null,
  "contributors": null,
  "is_quote_status": false,
  "retweet_count": 0,
  "favorite_count": 9,
  "favorited": false,
  "retweeted": false,
  "lang": "en"
}